[ {
  "id" : "ce6dade8-ac12-5b1a-3dff-2a81c99c086c",
  "name" : "icon",
  "label" : "Icon",
  "required" : false,
  "locked" : false,
  "responsive" : true,
  "resizable" : true,
  "show_loading" : false,
  "type" : "image",
  "display_width" : null,
  "default" : {
    "size_type" : "auto",
    "src" : "",
    "alt" : null,
    "loading" : "lazy"
  }
}, {
  "id" : "ffa2200e-5521-ddd4-a6be-312f2aac9618",
  "name" : "eyebrow_text",
  "label" : "Eyebrow Text",
  "required" : false,
  "locked" : false,
  "allow_new_line" : false,
  "type" : "text",
  "display_width" : null
} ]